{
	"editor": {
		"allAngles": false,
		"entityTextureMode": false
	},
	"textureWidth": 16,
	"textureHeight": 16,
	"textureSizes": {
	},
	"textures": {
	},
	"elements": [
		{
			"name": "minute",
			"from": [ 8.5, 7.9, 7.7 ],
			"to": [ 8.5, 7.9, 7.7 ],
			"rotationOrigin": [ 8.0, 8.15, 8.0 ],
			"rotationX": 90.0,
			"faces": {
				"north": { "texture": "#null", "uv": [ 13.5, 14.0, 14.0, 14.5 ] },
				"east": { "texture": "#null", "uv": [ 4.0, 2.0, 4.5, 2.5 ] },
				"south": { "texture": "#null", "uv": [ 10.0, 11.5, 10.5, 12.0 ] },
				"west": { "texture": "#null", "uv": [ 2.0, 4.5, 2.5, 5.0 ] },
				"up": { "texture": "#null", "uv": [ 9.0, 7.0, 9.5, 7.5 ] },
				"down": { "texture": "#null", "uv": [ 3.5, 3.0, 4.0, 3.5 ] }
			},
			"children": [
				{
					"name": "segment m1",
					"from": [ -1.5009, 0.1, -0.699 ],
					"to": [ -0.5009, 0.4, 2.301 ],
					"rotationOrigin": [ -0.5, 0.1, 0.8 ],
					"rotationY": 89.98,
					"faces": {
						"north": { "texture": "#minutehand", "uv": [ 5.5, 9.0, 6.5, 9.5 ] },
						"east": { "texture": "#minutehand", "uv": [ 8.5, 0.0, 11.5, 0.5 ] },
						"south": { "texture": "#minutehand", "uv": [ 3.0, 2.5, 4.0, 3.0 ] },
						"west": { "texture": "#minutehand", "uv": [ 10.5, 4.5, 13.5, 5.0 ] },
						"up": { "texture": "#minutehand", "uv": [ 11.5, 6.5, 12.5, 9.5 ] },
						"down": { "texture": "#minutehand", "uv": [ 12.5, 4.5, 13.5, 7.5 ] }
					},
					"children": [
						{
							"name": "segment m2",
							"from": [ 2.0, 0.0, 0.0 ],
							"to": [ 3.0, 0.3, 3.0 ],
							"rotationOrigin": [ 2.0, 0.0, 1.5 ],
							"faces": {
								"north": { "texture": "#minutehand", "uv": [ 9.5, 9.0, 10.5, 9.5 ] },
								"east": { "texture": "#minutehand", "uv": [ 0.5, 6.5, 3.5, 7.0 ] },
								"south": { "texture": "#minutehand", "uv": [ 11.0, 7.0, 12.0, 7.5 ] },
								"west": { "texture": "#minutehand", "uv": [ 2.0, 6.5, 5.0, 7.0 ] },
								"up": { "texture": "#minutehand", "uv": [ 14.0, 4.0, 15.0, 7.0 ] },
								"down": { "texture": "#minutehand", "uv": [ 2.5, 3.5, 3.5, 6.5 ] }
							},
							"children": [
								{
									"name": "segment m3",
									"from": [ -1.0, 0.0, 0.0 ],
									"to": [ 0.0, 0.3, 1.0 ],
									"rotationOrigin": [ -0.5, 0.0, 1.5 ],
									"faces": {
										"north": { "texture": "#minutehand", "uv": [ 11.5, 6.0, 12.5, 6.5 ] },
										"south": { "texture": "#minutehand", "uv": [ 5.5, 5.5, 6.5, 6.0 ] },
										"up": { "texture": "#minutehand", "uv": [ 7.0, 6.5, 8.0, 7.5 ] },
										"down": { "texture": "#minutehand", "uv": [ 10.5, 0.5, 11.5, 1.5 ] }
									}
								},
								{
									"name": "segment m4",
									"from": [ -1.0, 0.0, 2.0 ],
									"to": [ 0.0, 0.3, 3.0 ],
									"rotationOrigin": [ -0.5, 0.0, 3.5 ],
									"faces": {
										"north": { "texture": "#minutehand", "uv": [ 0.5, 4.5, 1.5, 5.0 ] },
										"south": { "texture": "#minutehand", "uv": [ 13.0, 12.0, 14.0, 12.5 ] },
										"up": { "texture": "#minutehand", "uv": [ 12.5, 10.5, 13.5, 11.5 ] },
										"down": { "texture": "#minutehand", "uv": [ 5.5, 3.0, 6.5, 4.0 ] }
									}
								}
							]
						},
						{
							"name": "segment m5",
							"from": [ 3.0, 0.0, 0.5 ],
							"to": [ 15.0, 0.3, 2.5 ],
							"rotationOrigin": [ 3.0, 0.0, 1.8 ],
							"faces": {
								"north": { "texture": "#minutehand", "uv": [ 3.5, 12.5, 15.5, 13.0 ] },
								"east": { "texture": "#minutehand", "uv": [ 5.5, 12.0, 7.5, 12.5 ] },
								"south": { "texture": "#minutehand", "uv": [ 2.5, 2.5, 14.5, 3.0 ] },
								"up": { "texture": "#minutehand", "uv": [ 3.5, 3.5, 15.5, 5.5 ] },
								"down": { "texture": "#minutehand", "uv": [ 2.5, 3.5, 14.5, 5.5 ] }
							},
							"children": [
								{
									"name": "segment m6",
									"from": [ 12.0, 0.0, 0.2 ],
									"to": [ 20.0, 0.3, 1.8 ],
									"rotationOrigin": [ 12.0, 0.0, 0.2 ],
									"faces": {
										"north": { "texture": "#minutehand", "uv": [ 5.0, 10.0, 13.0, 10.5 ] },
										"east": { "texture": "#minutehand", "uv": [ 6.5, 5.0, 8.0, 5.5 ] },
										"south": { "texture": "#minutehand", "uv": [ 1.5, 6.0, 9.5, 6.5 ] },
										"up": { "texture": "#minutehand", "uv": [ 3.5, 9.5, 11.5, 11.0 ] },
										"down": { "texture": "#minutehand", "uv": [ 2.5, 8.5, 10.5, 10.0 ] }
									},
									"children": [
										{
											"name": "segment m7",
											"from": [ 8.0, 0.0, 0.2 ],
											"to": [ 14.5, 0.3, 1.4 ],
											"rotationOrigin": [ 8.0, 0.0, 0.2 ],
											"faces": {
												"north": { "texture": "#minutehand", "uv": [ 2.5, 10.5, 9.0, 11.0 ] },
												"east": { "texture": "#minutehand", "uv": [ 2.5, 9.5, 3.5, 10.0 ] },
												"south": { "texture": "#minutehand", "uv": [ 3.5, 12.0, 10.0, 12.5 ] },
												"up": { "texture": "#minutehand", "uv": [ 5.0, 3.0, 11.5, 4.0 ] },
												"down": { "texture": "#minutehand", "uv": [ 6.0, 5.0, 12.5, 6.0 ] }
											},
											"children": [
												{
													"name": "segment m8",
													"from": [ 6.5, 0.0, 0.2 ],
													"to": [ 11.5, 0.3, 1.0 ],
													"rotationOrigin": [ 6.5, 0.0, 0.2 ],
													"faces": {
														"north": { "texture": "#minutehand", "uv": [ 6.5, 9.5, 11.5, 10.0 ] },
														"east": { "texture": "#minutehand", "uv": [ 13.0, 12.0, 13.5, 12.5 ] },
														"south": { "texture": "#minutehand", "uv": [ 6.5, 4.5, 11.5, 5.0 ] },
														"up": { "texture": "#minutehand", "uv": [ 8.0, 0.5, 13.0, 1.0 ] },
														"down": { "texture": "#minutehand", "uv": [ 0.5, 3.5, 5.5, 4.0 ] }
													}
												}
											]
										}
									]
								}
							]
						},
						{
							"name": "segment m10",
							"from": [ -3.4993, -3.0E-4, 0.9974 ],
							"to": [ -1.4993, 0.2997, 1.9974 ],
							"rotationOrigin": [ -3.4999, 0.0, 1.0 ],
							"rotationY": 0.02,
							"rotationZ": -0.003,
							"faces": {
								"north": { "texture": "#minutehand", "uv": [ 4.5, 9.5, 6.5, 10.0 ] },
								"south": { "texture": "#minutehand", "uv": [ 8.5, 9.5, 10.5, 10.0 ] },
								"west": { "texture": "#minutehand", "uv": [ 9.5, 10.5, 10.5, 11.0 ] },
								"up": { "texture": "#minutehand", "uv": [ 7.5, 13.0, 9.5, 14.0 ] },
								"down": { "texture": "#minutehand", "uv": [ 1.5, 6.0, 3.5, 7.0 ] }
							},
							"children": [
								{
									"name": "segment m9",
									"from": [ 1.999, 0.1015, -0.3468 ],
									"to": [ 3.499, 1.6015, -0.0468 ],
									"rotationOrigin": [ 1.999, 0.1005, -0.2468 ],
									"rotationX": -90.0,
									"rotationY": -0.003,
									"rotationZ": -89.995,
									"faces": {
										"north": { "texture": "#minutehand", "uv": [ 2.5, 10.0, 4.0, 11.5 ] },
										"east": { "texture": "#minutehand", "uv": [ 7.0, 12.5, 7.5, 14.0 ] },
										"south": { "texture": "#minutehand", "uv": [ 0.5, 0.5, 2.0, 2.0 ] },
										"west": { "texture": "#minutehand", "uv": [ 0.5, 10.0, 1.0, 11.5 ] },
										"down": { "texture": "#minutehand", "uv": [ 9.5, 8.0, 11.0, 8.5 ] }
									}
								}
							]
						}
					]
				}
			]
		}
	]}